MANIFEST.in
README.md
setup.cfg
setup.py
libffpy/__init__.py
libffpy/libff_wrapper.cpp
libffpy/libff_wrapper.h
libffpy/libffpy.cpp
libffpy/libffpy.pxd
libffpy/libffpy.pyx
libffpy.egg-info/PKG-INFO
libffpy.egg-info/SOURCES.txt
libffpy.egg-info/dependency_links.txt
libffpy.egg-info/requires.txt
libffpy.egg-info/top_level.txt
libffpy/libff/build/depends/libzm.a
libffpy/libff/depends/ate-pairing/include/bn.h
libffpy/libff/depends/ate-pairing/include/zm.h
libffpy/libff/depends/ate-pairing/include/zm2.h
libffpy/libff/depends/ate-pairing/include/cybozu/benchmark.hpp
libffpy/libff/depends/ate-pairing/include/cybozu/inttype.hpp
libffpy/libff/depends/ate-pairing/include/cybozu/readme.txt
libffpy/libff/depends/ate-pairing/include/cybozu/test.hpp
libffpy/libff/include/libff/algebra/curves/curve_utils.hpp
libffpy/libff/include/libff/algebra/curves/curve_utils.tcc
libffpy/libff/include/libff/algebra/curves/public_params.hpp
libffpy/libff/include/libff/algebra/curves/alt_bn128/alt_bn128_g1.hpp
libffpy/libff/include/libff/algebra/curves/alt_bn128/alt_bn128_g2.hpp
libffpy/libff/include/libff/algebra/curves/alt_bn128/alt_bn128_init.hpp
libffpy/libff/include/libff/algebra/curves/alt_bn128/alt_bn128_pairing.hpp
libffpy/libff/include/libff/algebra/curves/alt_bn128/alt_bn128_pp.hpp
libffpy/libff/include/libff/algebra/curves/bn128/bn128_g1.hpp
libffpy/libff/include/libff/algebra/curves/bn128/bn128_g2.hpp
libffpy/libff/include/libff/algebra/curves/bn128/bn128_gt.hpp
libffpy/libff/include/libff/algebra/curves/bn128/bn128_init.hpp
libffpy/libff/include/libff/algebra/curves/bn128/bn128_pairing.hpp
libffpy/libff/include/libff/algebra/curves/bn128/bn128_pp.hpp
libffpy/libff/include/libff/algebra/curves/bn128/bn_utils.hpp
libffpy/libff/include/libff/algebra/curves/bn128/bn_utils.tcc
libffpy/libff/include/libff/algebra/curves/edwards/edwards_g1.hpp
libffpy/libff/include/libff/algebra/curves/edwards/edwards_g2.hpp
libffpy/libff/include/libff/algebra/curves/edwards/edwards_init.hpp
libffpy/libff/include/libff/algebra/curves/edwards/edwards_pairing.hpp
libffpy/libff/include/libff/algebra/curves/edwards/edwards_pp.hpp
